microbit/GPIO.py
microbit/__init__.py
microbit/api.py
microbit/font2x5.py
microbit/microbits.py
microbit/test_repl.py
microbit/drivescan/README.txt
microbit/portscan/README.txt
microbit/portscan/__init__.py
microbit/portscan/ports_unix.py
microbit/portscan/ports_win32.py
microbit/repl/README.txt
microbit/repl/__init__.py
microbit/repl/repl.py
microbit/serial/LICENSE.txt
microbit/serial/TRACEABILITY.txt
microbit/serial/__init__.py
microbit/serial/rfc2217.py
microbit/serial/rs485.py
microbit/serial/serialcli.py
microbit/serial/serialjava.py
microbit/serial/serialposix.py
microbit/serial/serialutil.py
microbit/serial/serialwin32.py
microbit/serial/win32.py
cs20_microbitio-0.2.dist-info/LICENSE
cs20_microbitio-0.2.dist-info/METADATA
cs20_microbitio-0.2.dist-info/WHEEL
cs20_microbitio-0.2.dist-info/top_level.txt
cs20_microbitio-0.2.dist-info/RECORD
